AlistMediaRename/__init__.py
AlistMediaRename/amr.py
AlistMediaRename/api.py
AlistMediaRename/cli.py
AlistMediaRename/config.py
AlistMediaRename/default.yaml
AlistMediaRename/logger_setup.py
AlistMediaRename/models.py
AlistMediaRename/output.py
AlistMediaRename/task.py
AlistMediaRename/utils.py
alistmediarename-3.3.1.dist-info/METADATA
alistmediarename-3.3.1.dist-info/WHEEL
alistmediarename-3.3.1.dist-info/entry_points.txt
alistmediarename-3.3.1.dist-info/licenses/LICENCE
alistmediarename-3.3.1.dist-info/RECORD
