Metadata-Version: 2.4
Name: AlistMediaRename
Version: 3.3.1
Summary: 从 The Movie Database(TMDb) 获取剧集/电影信息，并对 Alist 指定媒体文件重命名，便于播放器刮削识别剧集/电影。测试Kodi, Nplayer, Infuse均可正确识别媒体信息。
Project-URL: Homepage, https://github.com/jkoor/Alist-Media-Rename
Author-email: Hardy <oharcy@outlook.com>
License-File: LICENCE
Requires-Python: >=3.9
Requires-Dist: click>=8.1.7
Requires-Dist: httpx>=0.28.1
Requires-Dist: natsort>=8.4.0
Requires-Dist: pydantic>=2.8.2
Requires-Dist: pyotp>=2.9.0
Requires-Dist: rich>=13.9.4
Requires-Dist: ruamel-yaml>=0.18.6
